mkdocs_merge-0.11.0.dist-info/licenses/LICENSE
mkdocsmerge/__init__.py
mkdocsmerge/__main__.py
mkdocsmerge/merge.py
mkdocsmerge/tests/__init__.py
mkdocsmerge/tests/copy_tree_test.py
mkdocsmerge/tests/merge_test.py
mkdocsmerge/tests/multiple_merge_test.py
mkdocsmerge/tests/run_merge_test.py
mkdocsmerge/tests/utils.py
mkdocs_merge-0.11.0.dist-info/METADATA
mkdocs_merge-0.11.0.dist-info/WHEEL
mkdocs_merge-0.11.0.dist-info/entry_points.txt
mkdocs_merge-0.11.0.dist-info/top_level.txt
mkdocs_merge-0.11.0.dist-info/RECORD
