Metadata-Version: 2.4
Name: mkdocs-merge
Version: 0.11.0
Summary: Tool to merge multiple MkDocs sites into a single directory
Author-email: Oscar Vasquez <oscar@vasquezcr.com>
License: MIT
Project-URL: homepage, https://github.com/ovasquez/mkdocs-merge
Project-URL: repository, https://github.com/ovasquez/mkdocs-merge
Project-URL: download, https://github.com/ovasquez/mkdocs-merge/archive/main.zip
Keywords: mkdocs,documentation,merge,multiple
Classifier: Development Status :: 4 - Beta
Classifier: Topic :: Documentation
Classifier: Topic :: Text Processing
Classifier: Environment :: Console
Classifier: Environment :: Web Environment
Classifier: License :: OSI Approved :: MIT License
Classifier: Programming Language :: Python :: 3
Classifier: Programming Language :: Python :: 3.8
Classifier: Programming Language :: Python :: 3.9
Classifier: Programming Language :: Python :: 3.10
License-File: LICENSE
Requires-Dist: click>=5.0
Requires-Dist: mkdocs>=1.0
Requires-Dist: ruamel.yaml>=0.17
Provides-Extra: dev
Requires-Dist: tox>=3.0; extra == "dev"
Requires-Dist: pytest; extra == "dev"
Requires-Dist: pytest-cov; extra == "dev"
Dynamic: license-file
